demos/__init__.py
demos/test.py
timeworker/__init__.py
timeworker/conf.py
timeworker/date.py
timeworker/date_parser.py
timeworker/freshness_date_parser.py
timeworker/parser.py
timeworker/timezone_parser.py
timeworker/timezones.py
timeworker/calendars/__init__.py
timeworker/calendars/hijri.py
timeworker/calendars/hijri_parser.py
timeworker/calendars/jalali.py
timeworker/calendars/jalali_parser.py
timeworker/custom_language_detection/__init__.py
timeworker/custom_language_detection/fasttext.py
timeworker/custom_language_detection/langdetect.py
timeworker/custom_language_detection/language_mapping.py
timeworker/data/__init__.py
timeworker/data/languages_info.py
timeworker/data/date_translation_data/__init__.py
timeworker/data/date_translation_data/zh-Hans.py
timeworker/languages/__init__.py
timeworker/languages/dictionary.py
timeworker/languages/loader.py
timeworker/languages/locale.py
timeworker/languages/validation.py
timeworker/search/__init__.py
timeworker/search/detection.py
timeworker/search/search.py
timeworker/search/text_detection.py
timeworker/utils/__init__.py
timeworker/utils/additional.py
timeworker/utils/strptime.py
timeworker_data/__init__.py
timeworker_data/settings.py
timeworker-1.3.2.dist-info/LICENSE
timeworker-1.3.2.dist-info/METADATA
timeworker-1.3.2.dist-info/WHEEL
timeworker-1.3.2.dist-info/top_level.txt
timeworker-1.3.2.dist-info/RECORD
