Metadata-Version: 2.1
Name: timeworker
Version: 1.3.2
Summary: A chinese time str normalization package
Home-page: https://github.com/yfzsj01/timeworker
Author: DanielZzzsj
Author-email: yfzsj01@gmail.com
Classifier: Development Status :: 3 - Alpha
Classifier: Programming Language :: Python :: 3
Classifier: License :: OSI Approved :: MIT License
Classifier: Operating System :: OS Independent
Requires-Python: >=3.6
License-File: LICENSE
Requires-Dist: python-dateutil
Requires-Dist: pytz
Requires-Dist: regex (!=2019.02.19,!=2021.8.27,<2022.3.15)
Requires-Dist: tzlocal
